lookml_visualizer/__init__.py
lookml_visualizer/grapher.py
lookml_visualizer/main.py
lookml_visualizer/visualizer.py
lookml_visualizer-0.3.dist-info/WHEEL
lookml_visualizer-0.3.dist-info/METADATA
lookml_visualizer-0.3.dist-info/RECORD
