Metadata-Version: 2.1
Name: lookml_visualizer
Version: 0.3
Summary: Visualize LookML relationships network as an interactive figure
Home-page: https://github.com/iamaziz/lookml_visualizer
License: UNKNOWN
Author: Aziz Alto
Author-email: iamaziz.alto@gmail.com
Requires-Dist: lookml-tools>=2.0.5
Requires-Dist: networkx==2.5
Requires-Dist: plotly==4.14.1
Requires-Dist: matplotlib==3.3.3
Requires-Dist: lkml==0.1.1
Requires-Dist: pydot==1.4.1
